msilib/_msi.cp313-win32.pyd
pymsilib/__init__.py
pymsilib/_msi.cp313-win32.pyd
pymsilib/schema.py
pymsilib/sequence.py
pymsilib/text.py
pymsilib-1.0.0.dist-info/LICENSE
pymsilib-1.0.0.dist-info/METADATA
pymsilib-1.0.0.dist-info/WHEEL
pymsilib-1.0.0.dist-info/top_level.txt
pymsilib-1.0.0.dist-info/RECORD
