Metadata-Version: 2.1
Name: pymsilib
Version: 1.0.0
Summary: Replacement for msilib
Home-page: https://github.com/TrevorHamm/msilib
Author: Trevor Hamm
Author-email: alohaeh@gmail.com
License: Python Software Foundation License
Requires-Python: >=3.13
License-File: LICENSE
